teams_memory/__init__.py
teams_memory/config.py
teams_memory/core/__init__.py
teams_memory/core/memory_core.py
teams_memory/core/memory_module.py
teams_memory/core/message_buffer.py
teams_memory/core/message_queue.py
teams_memory/core/prompts.py
teams_memory/interfaces/__init__.py
teams_memory/interfaces/base_memory_core.py
teams_memory/interfaces/base_memory_module.py
teams_memory/interfaces/base_memory_storage.py
teams_memory/interfaces/base_message_buffer_storage.py
teams_memory/interfaces/base_message_queue.py
teams_memory/interfaces/base_message_storage.py
teams_memory/interfaces/base_scheduled_events_service.py
teams_memory/interfaces/base_scheduled_events_storage.py
teams_memory/interfaces/errors.py
teams_memory/interfaces/types.py
teams_memory/services/__init__.py
teams_memory/services/llm_service.py
teams_memory/services/scheduled_events_service.py
teams_memory/storage/azure_ai_search.py
teams_memory/storage/in_memory_storage.py
teams_memory/storage/migrations_manager.py
teams_memory/storage/sqlite_memory_storage.py
teams_memory/storage/sqlite_message_buffer_storage.py
teams_memory/storage/sqlite_message_storage.py
teams_memory/storage/sqlite_scheduled_events_storage.py
teams_memory/storage/sqlite_storage.py
teams_memory/storage/utils.py
teams_memory/storage/migrations/1_initial_schema.sql
teams_memory/utils/logging.py
teams_memory/utils/teams_bot_middlware.py
teams_memory-0.1.4a0.dist-info/METADATA
teams_memory-0.1.4a0.dist-info/WHEEL
teams_memory-0.1.4a0.dist-info/licenses/LICENSE
teams_memory-0.1.4a0.dist-info/RECORD
