Metadata-Version: 2.4
Name: teams_memory
Version: 0.1.4a0
Summary: Memory module for creating intelligent agents within Microsoft Teams
Project-URL: Homepage, https://github.com/microsoft/teams-agent-accelerator-libs-py/tree/main/packages/teams_memory
Author-email: Microsoft <teams@microsoft.com>
License-Expression: MIT
License-File: LICENSE
Keywords: accelerator,agents,ai,bot,memory,microsoft,teams
Requires-Python: >=3.12
Requires-Dist: aiosqlite>=0.20.0
Requires-Dist: botbuilder>=0.0.1
Requires-Dist: botframework-connector>=4.16.2
Requires-Dist: instructor>=1.6.4
Requires-Dist: litellm==1.69.2
Requires-Dist: numpy
Requires-Dist: pydantic>=2.10.1
Requires-Dist: python-dotenv>=1.0.1
Requires-Dist: sqlite-vec>=0.1.6
Provides-Extra: azure-search
Requires-Dist: aiohttp>=3.10.5; extra == 'azure-search'
Requires-Dist: azure-search-documents>=11.5.2; extra == 'azure-search'
